quicksample.py
quicksampleYentim0519-0.0.1.dist-info/METADATA
quicksampleYentim0519-0.0.1.dist-info/WHEEL
quicksampleYentim0519-0.0.1.dist-info/top_level.txt
quicksampleYentim0519-0.0.1.dist-info/RECORD
