Metadata-Version: 2.1
Name: quicksampleYentim0519
Version: 0.0.1
Summary: Quicksample Test Package for SQLShack Demo
Author: Ting Yen
Classifier: Programming Language :: Python :: 3
Classifier: License :: OSI Approved :: MIT License
Classifier: Operating System :: OS Independent
Requires-Python: >=3.6
